setup.py
src/ZPublisherEventsBackport/__init__.py
src/ZPublisherEventsBackport/configure.zcml
src/ZPublisherEventsBackport/interfaces.py
src/ZPublisherEventsBackport/patch.py
src/ZPublisherEventsBackport/pubevents.py
src/ZPublisherEventsBackport.egg-info/PKG-INFO
src/ZPublisherEventsBackport.egg-info/SOURCES.txt
src/ZPublisherEventsBackport.egg-info/dependency_links.txt
src/ZPublisherEventsBackport.egg-info/not-zip-safe
src/ZPublisherEventsBackport.egg-info/requires.txt
src/ZPublisherEventsBackport.egg-info/top_level.txt