Metadata-Version: 1.0
Name: ZPublisherEventsBackport
Version: 1.1
Summary: Backport publication events from Zope 2.12 ZPublisher to Zope 2.10
Home-page: UNKNOWN
Author: Laurence Rowe
Author-email: laurence@lrowe.co.uk
License: ZPL
Platform: UNKNOWN
Classifier: Programming Language :: Python
Classifier: Environment :: Web Environment
Classifier: Framework :: Zope2
Classifier: Intended Audience :: Developers
Classifier: License :: OSI Approved :: Zope Public License
Classifier: Topic :: Software Development :: Libraries :: Python Modules
